AzureTokenVerification/__init__.py
AzureTokenVerification/exceptions.py
AzureTokenVerification/token_verifier.py
AzureTokenVerification-0.0.5.dist-info/LICENSE
AzureTokenVerification-0.0.5.dist-info/METADATA
AzureTokenVerification-0.0.5.dist-info/WHEEL
AzureTokenVerification-0.0.5.dist-info/top_level.txt
AzureTokenVerification-0.0.5.dist-info/RECORD
